README.md
deepstruct/__init__.py
deepstruct/__version__.py
deepstruct/dataset.py
deepstruct/graph.py
deepstruct/learning.py
deepstruct/pruning.py
deepstruct/recurrent.py
deepstruct/scalable.py
deepstruct/sparse.py
deepstruct/transform.py
deepstruct/util.py
pyproject.toml
deepstruct-0.10.0.dist-info/LICENSE.txt
deepstruct-0.10.0.dist-info/METADATA
deepstruct-0.10.0.dist-info/WHEEL
deepstruct-0.10.0.dist-info/RECORD
