Metadata-Version: 2.1
Name: deepstruct
Version: 0.10.0
Summary: 
Home-page: https://github.com/innvariant/deepstruct
License: MIT
Keywords: neural network,sparsity,machine learning,structure,graph,training
Author: Julian Stier
Author-email: julian.stier@uni-passau.de
Requires-Python: >=3.8,<4.0
Classifier: License :: OSI Approved :: MIT License
Classifier: Programming Language :: Python :: 3
Classifier: Programming Language :: Python :: 3.8
Classifier: Programming Language :: Python :: 3.9
Classifier: Programming Language :: Python :: 3.10
Classifier: Programming Language :: Python :: 3.11
Requires-Dist: deprecated (>=1.2.10,<2.0.0)
Requires-Dist: importlib-metadata (>=4.4,<5.0)
Requires-Dist: importlib-resources (>=5.0,<6.0)
Requires-Dist: networkx (>=2.0,<3.0)
Requires-Dist: numpy (>=1.21,<2.0)
Requires-Dist: semantic_version (>=2.10,<3.0)
Requires-Dist: torch (>=1.7,<2.0)
Project-URL: Documentation, https://deepstruct.readthedocs.io
Project-URL: Repository, https://github.com/innvariant/deepstruct
